LICENSE
MANIFEST.in
README.md
README.rst
run_tests.py
setup.cfg
setup.py
IfxAlchemy/IfxPy.py
IfxAlchemy/__init__.py
IfxAlchemy/base.py
IfxAlchemy/pyodbc.py
IfxAlchemy/reflection.py
IfxAlchemy/requirements.py
IfxAlchemy.egg-info/PKG-INFO
IfxAlchemy.egg-info/SOURCES.txt
IfxAlchemy.egg-info/dependency_links.txt
IfxAlchemy.egg-info/entry_points.txt
IfxAlchemy.egg-info/not-zip-safe
IfxAlchemy.egg-info/requires.txt
IfxAlchemy.egg-info/top_level.txt
test/__init__.py
test/test_001_CRUD.py
test/test_002_Extended_DataType.py
test/test_out_parameters.py
test/test_suite.py