Metadata-Version: 2.1
Name: IfxAlchemy
Version: 1.0.1
Summary: SQLAlchemy support for Informix Servers
Home-page: http://pypi.python.org/pypi/IfxAlchemy/
Author: OpenInformix Development Team
License: Apache License 2.0
Keywords: sqlalchemy database interface for Informix servers
Platform: All
License-File: LICENSE
